README
setup.py
seefeel/__init__.py
seefeel/clean.py
seefeel/clusterutils.py
seefeel/stop_words.txt
seefeel/stringutils.py
seefeel/textutils.py
seefeel/tokenizer.py
seefeel.egg-info/PKG-INFO
seefeel.egg-info/SOURCES.txt
seefeel.egg-info/dependency_links.txt
seefeel.egg-info/not-zip-safe
seefeel.egg-info/top_level.txt