Metadata-Version: 1.0
Name: seefeel
Version: 0.1.1
Summary: utils for text preprocess
Home-page: https://github.com/LeslieFire/seefeel
Author: seefeel
Author-email: 249893977@qq.com
License: MIT
Platform: UNKNOWN
